classic/error_handling/__init__.py
classic/error_handling/errors.py
classic/error_handling/utils.py
classic_error_handling-0.2.3.dist-info/licenses/LICENSE
classic_error_handling-0.2.3.dist-info/METADATA
classic_error_handling-0.2.3.dist-info/WHEEL
classic_error_handling-0.2.3.dist-info/top_level.txt
classic_error_handling-0.2.3.dist-info/RECORD
